ftiPackage/__init__.py
ftiPackage/bar_chart_module/__init__.py
ftiPackage/bar_chart_module/bar_chart_module.py
ftiPackage/base_chart_module/__init__.py
ftiPackage/base_chart_module/base_chart.py
ftiPackage/circle_packing_chart_module/__init__.py
ftiPackage/circle_packing_chart_module/circle_packing_chart.py
ftiPackage/hierarchical_network_chart/__init__.py
ftiPackage/hierarchical_network_chart/hierarchical_network_chart.py
ftiPackage/radar_chart_module/__init__.py
ftiPackage/radar_chart_module/radar_chart.py
ftiPackage/scatter_plot_module/__init__.py
ftiPackage/scatter_plot_module/scatter_plot.py
ftiPackage-0.1.0.dist-info/METADATA
ftiPackage-0.1.0.dist-info/WHEEL
ftiPackage-0.1.0.dist-info/top_level.txt
ftiPackage-0.1.0.dist-info/RECORD
