Metadata-Version: 2.1
Name: ftiPackage
Version: 0.1.0
Summary: The FTI Visualization Package is designed to create customizable data visualizations tailored to FTI's needs.
Home-page: https://github.com/asadrk988/ftiPackage.git
Author: Asad
Author-email: asadrk988@gmail.com
Requires-Dist: pandas
Requires-Dist: plotly
Requires-Dist: pytest
Requires-Dist: matplotlib
Requires-Dist: circlify
